CHANGELOG.md
neptune_tensorflow_keras/__init__.py
neptune_tensorflow_keras/impl/__init__.py
neptune_tensorflow_keras/impl/version.py
neptune_tensorflow_keras-2.2.2.dist-info/LICENSE
neptune_tensorflow_keras-2.2.2.dist-info/METADATA
neptune_tensorflow_keras-2.2.2.dist-info/WHEEL
neptune_tensorflow_keras-2.2.2.dist-info/RECORD
